PyWeekends/__init__.py
PyWeekends/__version__.py
PyWeekends/output_formatter.py
PyWeekends/weekend.py
tests/__init__.py
tests/test_output_formatter.py
tests/test_weekend.py
PyWeekends-0.0.2.dist-info/LICENSE
PyWeekends-0.0.2.dist-info/METADATA
PyWeekends-0.0.2.dist-info/WHEEL
PyWeekends-0.0.2.dist-info/top_level.txt
PyWeekends-0.0.2.dist-info/RECORD
