Metadata-Version: 2.1
Name: PyWeekends
Version: 0.0.2
Summary: A simple Python Weekends lib
Home-page: https://github.com/vubon/PyWeekends.git
Author: Vubon Roy
Author-email: vubon.roy@gmail.com
License: MIT
Classifier: Programming Language :: Python :: 3
Classifier: License :: OSI Approved :: MIT License
Classifier: Operating System :: OS Independent
Requires-Python: >=3.9
License-File: LICENSE
